{
  "inputs": [
    {
      "name": "a",
      "public": false,
      "type": "field"
    },
    {
      "name": "b",
      "public": false,
      "type": "field"
    },
    {
      "name": "c",
      "public": false,
      "type": "field"
    },
    {
      "name": "d",
      "public": false,
      "type": "field"
    },
    {
      "name": "k",
      "public": true,
      "type": "array",
      "components": {
        "size": 2,
        "type": "field"
      }
    }
  ],
  "output": {
    "type": "bool"
  }
}